README.md
setup.py
plotschedule/__init__.py
plotschedule/plot.py
plotschedule/plotSchedule.py
plotschedule.egg-info/PKG-INFO
plotschedule.egg-info/SOURCES.txt
plotschedule.egg-info/dependency_links.txt
plotschedule.egg-info/entry_points.txt
plotschedule.egg-info/not-zip-safe
plotschedule.egg-info/requires.txt
plotschedule.egg-info/top_level.txt