Metadata-Version: 2.1
Name: plotschedule
Version: 0.15
Summary: A simple matplotlib based schedule plotter
Home-page: https://github.com/sspickle/plotschedule
Author: Steve Spicklemire
Author-email: steve@spvi.com
License: MIT
Platform: UNKNOWN
